adp_connectors/__init__.py
adp_connectors/base.py
adp_connectors/box.py
adp_connectors/postgresql.py
adp_connectors/s3.py
adp_connectors-0.1.1.dist-info/LICENSE
adp_connectors-0.1.1.dist-info/METADATA
adp_connectors-0.1.1.dist-info/WHEEL
adp_connectors-0.1.1.dist-info/top_level.txt
adp_connectors-0.1.1.dist-info/RECORD
