Metadata-Version: 2.1
Name: adp-connectors
Version: 0.1.1
Summary: connection clients for storage and database
Author: Hongfei Tian
Author-email: hongfei.tian@ibm.com
Keywords: connector,storage,database
Classifier: Development Status :: 3 - Alpha
Classifier: Intended Audience :: Developers
Classifier: Topic :: Software Development :: Build Tools
Classifier: License :: OSI Approved :: MIT License
Classifier: Programming Language :: Python :: 3
Classifier: Programming Language :: Python :: 3.8
Classifier: Programming Language :: Python :: 3.9
Classifier: Programming Language :: Python :: 3.10
Classifier: Programming Language :: Python :: 3 :: Only
Requires-Python: >=3.8, <4
License-File: LICENSE
Requires-Dist: pandas
Requires-Dist: boto3
Requires-Dist: boxsdk[jwt]
Requires-Dist: psycopg2-binary ; platform_system != "Windows"
Requires-Dist: psycopg2 ; platform_system == "Windows"
